.pre-commit-config.yaml
.readthedocs.yaml
another_module/__init__.py
another_module/__main__.py
docker-compose.yaml
binary_module/__init__.py
binary_module/__main__.py
binary_module/add.py
learn_python/__init__.py
learn_python/__main__.py
learn_python/second/__init__.py
learn_python/second/__main__.py
learn_python/second/fourth.py
learn_python/second/third/__init__.py
library_module/__init__.py
library_module/_private.py
library_module/_private_dir_module/__init__.py
library_module/_private_dir_module/_private.py
library_module/_private_dir_module/public.py
library_module/chains/__init__.py
library_module/chains/_chain2.py
library_module/chains/_chain3.py
library_module/chains/chain1.py
library_module/circular_modules_1.py
library_module/circular_modules_2.py
library_module/circular_objects_1.py
library_module/circular_objects_2.py
library_module/just_dir/foo.py
library_module/public.py
library_module/public_alias.py
library_module/public_dir_module/__init__.py
library_module/public_dir_module/_bar.py
library_module/public_dir_module/foo.py
single_file_module.py
lpk-0.2.0.dist-info/METADATA
lpk-0.2.0.dist-info/WHEEL
lpk-0.2.0.dist-info/LICENSE
lpk-0.2.0.dist-info/entry_points.txt
lpk-0.2.0.dist-info/RECORD
