Metadata-Version: 2.1
Name: lpk
Version: 0.2.0
Summary: learning python
Home-page: https://github.com/kagemeka/learn-python#readme
License: Apache-2.0
Keywords: project,learning,packaging
Author: kagemeka
Author-email: kagemeka1@gmail.com
Maintainer: kagemeka
Maintainer-email: kagemeka1@gmail.com
Requires-Python: >=3.10,<3.12
Classifier: License :: OSI Approved :: Apache Software License
Classifier: License :: OSI Approved :: MIT License
Classifier: Operating System :: OS Independent
Classifier: Programming Language :: Python :: 3
Classifier: Programming Language :: Python :: 3.10
Classifier: Programming Language :: Python :: 3.11
Classifier: Programming Language :: Python :: 3
Classifier: Topic :: Software Development :: Libraries :: Python Modules
Provides-Extra: nb
Provides-Extra: np
Requires-Dist: numba (>=0.56.4,<0.57.0) ; extra == "nb"
Requires-Dist: numpy (>=1,<2) ; (python_version >= "3.11") and (extra == "np")
Requires-Dist: numpy (>=1.23,<2.0) ; (python_version < "3.11") and (extra == "np")
Requires-Dist: scipy (>=1.10,<1.11) ; extra == "np"
Project-URL: Documentation, https://kagemeka.github.io/learn-python
Project-URL: Repository, https://github.com/kagemeka/learn-python
Project-URL: rtd_document, https://lpk.readthedocs.io/en/latest/
